{
  "202212051200": {
    "제목": "풍랑주의보 해제",
    "해당구역": "(1) 풍랑주의보 해제 : 서해남부남쪽안쪽먼바다, 서해남부남쪽바깥먼바다, 남해동부바깥먼바다, 제주도앞바다(제주도서부앞바다)",
    "발효시각": "(1) 풍랑주의보 해제 : 2022년 12월 05일 15시 00분",
    "내용": "",
    "특보발효현황내용": 202212051500,
    "예비특보": "o 풍랑주의보 : 제주도남쪽바깥먼바다, 제주도남동쪽안쪽먼바다, 제주도남서쪽안쪽먼바다\r\no 건조경보 : 강원도(강릉평지, 동해평지, 삼척평지, 속초평지, 고성평지, 양양평지)\r\no 건조주의보 : 경기도(광명, 과천, 성남, 안양, 구리, 군포, 의왕, 하남, 광주), 강원도(태백, 정선평지, 철원, 화천, 강원북부산지, 강원중부산지, 강원남부산지), 충청북도(청주), 전라남도(광양, 순천), 경상북도(구미, 경산, 성주, 영덕, 울진평지, 포항, 경주, 경북북동산지), 경상남도(양산, 창원, 김해, 밀양, 진주, 함양, 사천), 서울, 광주, 대구, 부산, 울산"
  },
  "202212051000": {
    "제목": "강풍주의보·한파경보·한파주의보 해제",
    "해당구역": "(1) 강풍주의보 해제 : 제주도(제주도서부)\r\n(2) 한파경보 해제 : 강원도(철원, 화천, 강원북부산지, 강원중부산지)\r\n(3) 한파주의보 해제 : 경기도(연천, 포천), 강원도(평창평지, 횡성, 홍천평지, 춘천, 양구평지, 인제평지, 강원남부산지)",
    "발효시각": "(1) 강풍주의보 해제 : 2022년 12월 05일 10시 00분\r\n(2) 한파경보 해제 : 2022년 12월 05일 10시 00분\r\n(3) 한파주의보 해제 : 2022년 12월 05일 10시 00분",
    "내용": "",
    "특보발효현황내용": 202212051000,
    "예비특보": "o 풍랑주의보 : 서해남부남쪽안쪽먼바다, 서해남부남쪽바깥먼바다, 남해동부바깥먼바다, 제주도앞바다(제주도서부앞바다), 제주도남쪽바깥먼바다, 제주도남동쪽안쪽먼바다, 제주도남서쪽안쪽먼바다\r\no 건조경보 : 강원도(강릉평지, 동해평지, 삼척평지, 속초평지, 고성평지, 양양평지)\r\no 건조주의보 : 경기도(광명, 과천, 성남, 안양, 구리, 군포, 의왕, 하남, 광주), 강원도(태백, 정선평지, 철원, 화천, 강원북부산지, 강원중부산지, 강원남부산지), 충청북도(청주), 전라남도(광양, 순천), 경상북도(구미, 경산, 성주, 영덕, 울진평지, 포항, 경주, 경북북동산지), 경상남도(양산, 창원, 김해, 밀양, 진주, 함양, 사천), 서울, 광주, 대구, 부산, 울산"
  },
  "202212050600": {
    "제목": "풍랑주의보 해제·풍랑주의보 변경",
    "해당구역": "(1) 풍랑주의보 변경 : 제주도남쪽바깥먼바다\r\n(2) 풍랑주의보 해제 : 남해서부서쪽먼바다",
    "발효시각": "(1) 풍랑주의보 변경 : 2022년 12월 05일 06시 00분\r\n(2) 풍랑주의보 해제 : 2022년 12월 05일 08시 00분",
    "내용": "(1) 풍랑주의보 변경\r\n  o 해제 예고: 6일 새벽(00시~03시)",
    "특보발효현황내용": 202212050800,
    "예비특보": "o 강풍주의보 : 제주도(제주도서부)\r\no 풍랑주의보 : 서해남부남쪽안쪽먼바다, 서해남부남쪽바깥먼바다, 남해동부바깥먼바다, 제주도앞바다(제주도서부앞바다), 제주도남쪽바깥먼바다, 제주도남동쪽안쪽먼바다, 제주도남서쪽안쪽먼바다\r\no 한파경보 : 강원도(철원, 화천, 강원북부산지, 강원중부산지)\r\no 한파주의보 : 경기도(연천, 포천), 강원도(평창평지, 횡성, 홍천평지, 춘천, 양구평지, 인제평지, 강원남부산지)\r\no 건조경보 : 강원도(강릉평지, 동해평지, 삼척평지, 속초평지, 고성평지, 양양평지)\r\no 건조주의보 : 경기도(광명, 과천, 성남, 안양, 구리, 군포, 의왕, 하남, 광주), 강원도(태백, 정선평지, 철원, 화천, 강원북부산지, 강원중부산지, 강원남부산지), 충청북도(청주), 전라남도(광양, 순천), 경상북도(구미, 경산, 성주, 영덕, 울진평지, 포항, 경주, 경북북동산지), 경상남도(양산, 창원, 김해, 밀양, 진주, 함양, 사천), 서울, 광주, 대구, 부산, 울산"
  },
  "202212042100": {
    "제목": "강풍주의보·풍랑주의보 해제",
    "해당구역": "(1) 강풍주의보 해제 : 울릉도.독도\r\n(2) 강풍주의보 해제 : 전라남도(신안(흑산면제외), 진도)\r\n(3) 풍랑주의보 해제 : 서해남부북쪽안쪽먼바다, 서해남부북쪽바깥먼바다\r\n(4) 강풍주의보 해제 : 전라남도(흑산도.홍도)\r\n(5) 풍랑주의보 해제 : 동해남부북쪽안쪽먼바다, 동해남부북쪽바깥먼바다, 동해중부안쪽먼바다, 동해중부바깥먼바다",
    "발효시각": "(1) 강풍주의보 해제 : 2022년 12월 04일 21시 00분\r\n(2) 강풍주의보 해제 : 2022년 12월 04일 22시 00분\r\n(3) 풍랑주의보 해제 : 2022년 12월 04일 22시 00분\r\n(4) 강풍주의보 해제 : 2022년 12월 05일 00시 00분\r\n(5) 풍랑주의보 해제 : 2022년 12월 05일 00시 00분",
    "내용": "",
    "특보발효현황내용": 202212050000,
    "예비특보": "o 강풍주의보 : 제주도(제주도서부)\r\no 풍랑경보 : 제주도남쪽바깥먼바다\r\no 풍랑주의보 : 서해남부남쪽안쪽먼바다, 서해남부남쪽바깥먼바다, 남해동부바깥먼바다, 남해서부서쪽먼바다, 제주도앞바다(제주도서부앞바다), 제주도남동쪽안쪽먼바다, 제주도남서쪽안쪽먼바다\r\no 한파경보 : 강원도(철원, 화천, 강원북부산지, 강원중부산지)\r\no 한파주의보 : 경기도(연천, 포천), 강원도(평창평지, 횡성, 홍천평지, 춘천, 양구평지, 인제평지, 강원남부산지)\r\no 건조경보 : 강원도(강릉평지, 동해평지, 삼척평지, 속초평지, 고성평지, 양양평지)\r\no 건조주의보 : 경기도(광명, 과천, 성남, 안양, 구리, 군포, 의왕, 하남, 광주), 강원도(태백, 정선평지, 철원, 화천, 강원북부산지, 강원중부산지, 강원남부산지), 충청북도(청주), 전라남도(광양, 순천), 경상북도(구미, 경산, 성주, 영덕, 울진평지, 포항, 경주, 경북북동산지), 경상남도(양산, 창원, 김해, 밀양, 진주, 함양, 사천), 서울, 광주, 대구, 부산, 울산"
  },
  "202212041500": {
    "제목": "강풍주의보·풍랑주의보 해제",
    "해당구역": "(1) 강풍주의보 해제 : 서해5도, 전라남도(목포)\r\n(2) 풍랑주의보 해제 : 서해중부안쪽먼바다, 서해중부바깥먼바다",
    "발효시각": "(1) 강풍주의보 해제 : 2022년 12월 04일 15시 00분\r\n(2) 풍랑주의보 해제 : 2022년 12월 04일 17시 00분",
    "내용": "",
    "특보발효현황내용": 202212041700,
    "예비특보": "o 강풍주의보 : 전라남도(신안(흑산면제외), 진도, 흑산도.홍도), 제주도(제주도서부), 울릉도.독도\r\no 풍랑경보 : 제주도남쪽바깥먼바다\r\no 풍랑주의보 : 동해남부북쪽안쪽먼바다, 동해남부북쪽바깥먼바다, 동해중부안쪽먼바다, 동해중부바깥먼바다, 서해남부북쪽안쪽먼바다, 서해남부북쪽바깥먼바다, 서해남부남쪽안쪽먼바다, 서해남부남쪽바깥먼바다, 남해동부바깥먼바다, 남해서부서쪽먼바다, 제주도앞바다(제주도서부앞바다), 제주도남동쪽안쪽먼바다, 제주도남서쪽안쪽먼바다\r\no 한파경보 : 강원도(철원, 화천, 강원북부산지, 강원중부산지)\r\no 한파주의보 : 경기도(연천, 포천), 강원도(평창평지, 횡성, 홍천평지, 춘천, 양구평지, 인제평지, 강원남부산지)\r\no 건조경보 : 강원도(강릉평지, 동해평지, 삼척평지, 속초평지, 고성평지, 양양평지)\r\no 건조주의보 : 경기도(광명, 과천, 성남, 안양, 구리, 군포, 의왕, 하남, 광주), 강원도(태백, 정선평지, 철원, 화천, 강원북부산지, 강원중부산지, 강원남부산지), 충청북도(청주), 전라남도(광양, 순천), 경상북도(구미, 경산, 성주, 영덕, 울진평지, 포항, 경주, 경북북동산지), 경상남도(양산, 창원, 김해, 밀양, 진주, 함양, 사천), 서울, 광주, 대구, 부산, 울산"
  },
  "202212041030": {
    "제목": "풍랑경보 변경",
    "해당구역": "(1) 풍랑경보 변경 : 제주도남쪽바깥먼바다",
    "발효시각": "(1) 풍랑경보 변경 : 2022년 12월 04일 11시 30분",
    "내용": "(1) 풍랑경보 변경\r\n  o 해제 예고: 6일 새벽(00시~03시)",
    "특보발효현황내용": 202212041130,
    "예비특보": "o 강풍주의보 : 서해5도, 전라남도(목포, 신안(흑산면제외), 진도, 흑산도.홍도), 제주도(제주도서부), 울릉도.독도\r\no 풍랑경보 : 제주도남쪽바깥먼바다\r\no 풍랑주의보 : 동해남부북쪽안쪽먼바다, 동해남부북쪽바깥먼바다, 동해중부안쪽먼바다, 동해중부바깥먼바다, 서해남부북쪽안쪽먼바다, 서해남부북쪽바깥먼바다, 서해남부남쪽안쪽먼바다, 서해남부남쪽바깥먼바다, 서해중부안쪽먼바다, 서해중부바깥먼바다, 남해동부바깥먼바다, 남해서부서쪽먼바다, 제주도앞바다(제주도서부앞바다), 제주도남동쪽안쪽먼바다, 제주도남서쪽안쪽먼바다\r\no 한파경보 : 강원도(철원, 화천, 강원북부산지, 강원중부산지)\r\no 한파주의보 : 경기도(연천, 포천), 강원도(평창평지, 횡성, 홍천평지, 춘천, 양구평지, 인제평지, 강원남부산지)\r\no 건조경보 : 강원도(강릉평지, 동해평지, 삼척평지, 속초평지, 고성평지, 양양평지)\r\no 건조주의보 : 경기도(광명, 과천, 성남, 안양, 구리, 군포, 의왕, 하남, 광주), 강원도(태백, 정선평지, 철원, 화천, 강원북부산지, 강원중부산지, 강원남부산지), 충청북도(청주), 전라남도(광양, 순천), 경상북도(구미, 경산, 성주, 영덕, 울진평지, 포항, 경주, 경북북동산지), 경상남도(양산, 창원, 김해, 밀양, 진주, 함양, 사천), 서울, 광주, 대구, 부산, 울산"
  },
  "202212041000": {
    "제목": "한파주의보 해제·건조경보 변경·건조주의보 발표",
    "해당구역": "(1) 한파주의보 해제 : 강원도(태백, 원주)\r\n(2) 건조주의보 발표 : 경기도(광명, 과천, 성남, 안양, 구리, 군포, 의왕, 하남, 광주), 강원도(정선평지, 철원, 화천), 충청북도(청주), 전라남도(광양, 순천), 경상북도(구미, 경산, 성주), 경상남도(진주, 함양, 사천), 서울, 광주, 대구\r\n(3) 건조경보 변경 : 강원도(강릉평지, 동해평지, 삼척평지, 속초평지, 고성평지, 양양평지)",
    "발효시각": "(1) 한파주의보 해제 : 2022년 12월 04일 10시 00분\r\n(2) 건조주의보 발표 : 2022년 12월 04일 10시 00분\r\n(3) 건조경보 변경 : 2022년 12월 04일 10시 00분",
    "내용": "",
    "특보발효현황내용": 202212041000,
    "예비특보": "o 강풍주의보 : 서해5도, 전라남도(목포, 신안(흑산면제외), 진도, 흑산도.홍도), 제주도(제주도서부), 울릉도.독도\r\no 풍랑주의보 : 동해남부북쪽안쪽먼바다, 동해남부북쪽바깥먼바다, 동해중부안쪽먼바다, 동해중부바깥먼바다, 서해남부북쪽안쪽먼바다, 서해남부북쪽바깥먼바다, 서해남부남쪽안쪽먼바다, 서해남부남쪽바깥먼바다, 서해중부안쪽먼바다, 서해중부바깥먼바다, 남해동부바깥먼바다, 남해서부서쪽먼바다, 제주도앞바다(제주도서부앞바다), 제주도남쪽바깥먼바다, 제주도남동쪽안쪽먼바다, 제주도남서쪽안쪽먼바다\r\no 한파경보 : 강원도(철원, 화천, 강원북부산지, 강원중부산지)\r\no 한파주의보 : 경기도(연천, 포천), 강원도(평창평지, 횡성, 홍천평지, 춘천, 양구평지, 인제평지, 강원남부산지)\r\no 건조경보 : 강원도(강릉평지, 동해평지, 삼척평지, 속초평지, 고성평지, 양양평지)\r\no 건조주의보 : 경기도(광명, 과천, 성남, 안양, 구리, 군포, 의왕, 하남, 광주), 강원도(태백, 정선평지, 철원, 화천, 강원북부산지, 강원중부산지, 강원남부산지), 충청북도(청주), 전라남도(광양, 순천), 경상북도(구미, 경산, 성주, 영덕, 울진평지, 포항, 경주, 경북북동산지), 경상남도(양산, 창원, 김해, 밀양, 진주, 함양, 사천), 서울, 광주, 대구, 부산, 울산"
  },
  "202212040600": {
    "제목": "풍랑주의보 발표",
    "해당구역": "(1) 풍랑주의보 발표 : 동해남부북쪽안쪽먼바다, 동해남부북쪽바깥먼바다\r\n(2) 풍랑주의보 발표 : 남해동부바깥먼바다",
    "발효시각": "(1) 풍랑주의보 발표 : 2022년 12월 04일 08시 00분\r\n(2) 풍랑주의보 발표 : 2022년 12월 04일 09시 00분",
    "내용": "(1) 풍랑주의보 발표\r\n  o 해제 예고: 5일 새벽(00시~03시)\r\n(2) 풍랑주의보 발표\r\n  o 해제 예고: 5일 늦은 오후(15시~18시)",
    "특보발효현황내용": 202212040900,
    "예비특보": "o 강풍주의보 : 서해5도, 전라남도(목포, 신안(흑산면제외), 진도, 흑산도.홍도), 제주도(제주도서부), 울릉도.독도\r\no 풍랑주의보 : 동해남부북쪽안쪽먼바다, 동해남부북쪽바깥먼바다, 동해중부안쪽먼바다, 동해중부바깥먼바다, 서해남부북쪽안쪽먼바다, 서해남부북쪽바깥먼바다, 서해남부남쪽안쪽먼바다, 서해남부남쪽바깥먼바다, 서해중부안쪽먼바다, 서해중부바깥먼바다, 남해동부바깥먼바다, 남해서부서쪽먼바다, 제주도앞바다(제주도서부앞바다), 제주도남쪽바깥먼바다, 제주도남동쪽안쪽먼바다, 제주도남서쪽안쪽먼바다\r\no 한파경보 : 강원도(철원, 화천, 강원북부산지, 강원중부산지)\r\no 한파주의보 : 경기도(연천, 포천), 강원도(태백, 평창평지, 횡성, 원주, 홍천평지, 춘천, 양구평지, 인제평지, 강원남부산지)\r\no 건조주의보 : 강원도(강릉평지, 동해평지, 태백, 삼척평지, 속초평지, 고성평지, 양양평지, 강원북부산지, 강원중부산지, 강원남부산지), 경상북도(영덕, 울진평지, 포항, 경주, 경북북동산지), 경상남도(양산, 창원, 김해, 밀양), 부산, 울산"
  },
  "202212040400": {
    "제목": "강풍주의보·풍랑주의보 발표",
    "해당구역": "(1) 강풍주의보 발표 : 전라남도(목포)\r\n(2) 강풍주의보 발표 : 제주도(제주도서부)\r\n(3) 풍랑주의보 발표 : 제주도앞바다(제주도서부앞바다)",
    "발효시각": "(1) 강풍주의보 발표 : 2022년 12월 04일 04시 00분\r\n(2) 강풍주의보 발표 : 2022년 12월 04일 06시 00분\r\n(3) 풍랑주의보 발표 : 2022년 12월 04일 06시 00분",
    "내용": "(1) 강풍주의보 발표\r\n  o 해제 예고: 4일 낮(12시~15시)\r\n(2) 강풍주의보 발표\r\n  o 해제 예고: 5일 늦은 오후(15시~18시)\r\n(3) 풍랑주의보 발표\r\n  o 해제 예고: 5일 늦은 오후(15시~18시)",
    "특보발효현황내용": 202212040600,
    "예비특보": "o 강풍주의보 : 서해5도, 전라남도(목포, 신안(흑산면제외), 진도, 흑산도.홍도), 제주도(제주도서부), 울릉도.독도\r\no 풍랑주의보 : 동해중부안쪽먼바다, 동해중부바깥먼바다, 서해남부북쪽안쪽먼바다, 서해남부북쪽바깥먼바다, 서해남부남쪽안쪽먼바다, 서해남부남쪽바깥먼바다, 서해중부안쪽먼바다, 서해중부바깥먼바다, 남해서부서쪽먼바다, 제주도앞바다(제주도서부앞바다), 제주도남쪽바깥먼바다, 제주도남동쪽안쪽먼바다, 제주도남서쪽안쪽먼바다\r\no 한파경보 : 강원도(철원, 화천, 강원북부산지, 강원중부산지)\r\no 한파주의보 : 경기도(연천, 포천), 강원도(태백, 평창평지, 횡성, 원주, 홍천평지, 춘천, 양구평지, 인제평지, 강원남부산지)\r\no 건조주의보 : 강원도(강릉평지, 동해평지, 태백, 삼척평지, 속초평지, 고성평지, 양양평지, 강원북부산지, 강원중부산지, 강원남부산지), 경상북도(영덕, 울진평지, 포항, 경주, 경북북동산지), 경상남도(양산, 창원, 김해, 밀양), 부산, 울산"
  },
  "202212040200": {
    "제목": "강풍주의보·풍랑주의보 발표",
    "해당구역": "(1) 풍랑주의보 발표 : 제주도남쪽바깥먼바다\r\n(2) 강풍주의보 발표 : 전라남도(신안(흑산면제외), 진도)\r\n(3) 풍랑주의보 발표 : 서해남부남쪽안쪽먼바다, 서해남부남쪽바깥먼바다, 남해서부서쪽먼바다\r\n(4) 풍랑주의보 발표 : 제주도남동쪽안쪽먼바다, 제주도남서쪽안쪽먼바다",
    "발효시각": "(1) 풍랑주의보 발표 : 2022년 12월 04일 03시 00분\r\n(2) 강풍주의보 발표 : 2022년 12월 04일 04시 00분\r\n(3) 풍랑주의보 발표 : 2022년 12월 04일 04시 00분\r\n(4) 풍랑주의보 발표 : 2022년 12월 04일 04시 00분",
    "내용": "(1) ,(4) 풍랑주의보 발표\r\n  o 해제 예고: 6일 새벽(00시~03시)\r\n(2) 강풍주의보 발표\r\n  o 해제 예고: 4일 밤(21시~24시)\r\n(3) 풍랑주의보 발표\r\n  o 해제 예고: 5일 오전(09시~12시)",
    "특보발효현황내용": 202212040400,
    "예비특보": "o 강풍주의보 : 서해5도, 전라남도(신안(흑산면제외), 진도, 흑산도.홍도), 울릉도.독도\r\no 풍랑주의보 : 동해중부안쪽먼바다, 동해중부바깥먼바다, 서해남부북쪽안쪽먼바다, 서해남부북쪽바깥먼바다, 서해남부남쪽안쪽먼바다, 서해남부남쪽바깥먼바다, 서해중부안쪽먼바다, 서해중부바깥먼바다, 남해서부서쪽먼바다, 제주도남쪽바깥먼바다, 제주도남동쪽안쪽먼바다, 제주도남서쪽안쪽먼바다\r\no 한파경보 : 강원도(철원, 화천, 강원북부산지, 강원중부산지)\r\no 한파주의보 : 경기도(연천, 포천), 강원도(태백, 평창평지, 횡성, 원주, 홍천평지, 춘천, 양구평지, 인제평지, 강원남부산지)\r\no 건조주의보 : 강원도(강릉평지, 동해평지, 태백, 삼척평지, 속초평지, 고성평지, 양양평지, 강원북부산지, 강원중부산지, 강원남부산지), 경상북도(영덕, 울진평지, 포항, 경주, 경북북동산지), 경상남도(양산, 창원, 김해, 밀양), 부산, 울산"
  },
  "202212040000": {
    "제목": "강풍주의보·풍랑주의보 발표",
    "해당구역": "(1) 강풍주의보 발표 : 서해5도\r\n(2) 풍랑주의보 발표 : 서해중부안쪽먼바다, 서해중부바깥먼바다\r\n(3) 강풍주의보 발표 : 전라남도(흑산도.홍도)\r\n(4) 풍랑주의보 발표 : 서해남부북쪽안쪽먼바다, 서해남부북쪽바깥먼바다",
    "발효시각": "(1) 강풍주의보 발표 : 2022년 12월 04일 00시 00분\r\n(2) 풍랑주의보 발표 : 2022년 12월 04일 01시 00분\r\n(3) 강풍주의보 발표 : 2022년 12월 04일 02시 00분\r\n(4) 풍랑주의보 발표 : 2022년 12월 04일 02시 00분",
    "내용": "(1) 강풍주의보 발표\r\n  o 해제 예고: 4일 낮(12시~15시)\r\n(2) 풍랑주의보 발표\r\n  o 해제 예고: 4일 낮(12시~15시)\r\n(3) 강풍주의보 발표\r\n  o 해제 예고: 4일 밤(21시~24시)\r\n(4) 풍랑주의보 발표\r\n  o 해제 예고: 4일 밤(21시~24시)",
    "특보발효현황내용": 202212040200,
    "예비특보": "o 강풍주의보 : 서해5도, 전라남도(흑산도.홍도), 울릉도.독도\r\no 풍랑주의보 : 동해중부안쪽먼바다, 동해중부바깥먼바다, 서해남부북쪽안쪽먼바다, 서해남부북쪽바깥먼바다, 서해중부안쪽먼바다, 서해중부바깥먼바다\r\no 한파경보 : 강원도(철원, 화천, 강원북부산지, 강원중부산지)\r\no 한파주의보 : 경기도(연천, 포천), 강원도(태백, 평창평지, 횡성, 원주, 홍천평지, 춘천, 양구평지, 인제평지, 강원남부산지)\r\no 건조주의보 : 강원도(강릉평지, 동해평지, 태백, 삼척평지, 속초평지, 고성평지, 양양평지, 강원북부산지, 강원중부산지, 강원남부산지), 경상북도(영덕, 울진평지, 포항, 경주, 경북북동산지), 경상남도(양산, 창원, 김해, 밀양), 부산, 울산"
  },
  "202212032200": {
    "제목": "강풍주의보 해제",
    "해당구역": "(1) 강풍주의보 해제 : 강원도(속초평지, 고성평지, 양양평지)\r\n(2) 강풍주의보 해제 : 강원도(태백, 정선평지, 강원북부산지, 강원중부산지, 강원남부산지)",
    "발효시각": "(1) 강풍주의보 해제 : 2022년 12월 03일 22시 00분\r\n(2) 강풍주의보 해제 : 2022년 12월 04일 01시 00분",
    "내용": "",
    "특보발효현황내용": 202212040100,
    "예비특보": "o 강풍주의보 : 울릉도.독도\r\no 풍랑주의보 : 동해중부안쪽먼바다, 동해중부바깥먼바다\r\no 한파경보 : 강원도(철원, 화천, 강원북부산지, 강원중부산지)\r\no 한파주의보 : 경기도(연천, 포천), 강원도(태백, 평창평지, 횡성, 원주, 홍천평지, 춘천, 양구평지, 인제평지, 강원남부산지)\r\no 건조주의보 : 강원도(강릉평지, 동해평지, 태백, 삼척평지, 속초평지, 고성평지, 양양평지, 강원북부산지, 강원중부산지, 강원남부산지), 경상북도(영덕, 울진평지, 포항, 경주, 경북북동산지), 경상남도(양산, 창원, 김해, 밀양), 부산, 울산"
  },
  "202212031700": {
    "제목": "강풍주의보 발표",
    "해당구역": "(1) 강풍주의보 발표 : 울릉도.독도",
    "발효시각": "(1) 강풍주의보 발표 : 2022년 12월 03일 18시 00분",
    "내용": "(1) 강풍주의보 발표\r\n  o 해제 예고: 5일 새벽(00시~03시)",
    "특보발효현황내용": 202212032300,
    "예비특보": "o 강풍주의보 : 강원도(태백, 속초평지, 고성평지, 양양평지, 정선평지, 강원북부산지, 강원중부산지, 강원남부산지), 울릉도.독도\r\no 풍랑주의보 : 동해중부안쪽먼바다, 동해중부바깥먼바다\r\no 한파경보 : 강원도(철원, 화천, 강원북부산지, 강원중부산지)\r\no 한파주의보 : 경기도(연천, 포천), 강원도(태백, 평창평지, 횡성, 원주, 홍천평지, 춘천, 양구평지, 인제평지, 강원남부산지)\r\no 건조주의보 : 강원도(강릉평지, 동해평지, 태백, 삼척평지, 속초평지, 고성평지, 양양평지, 강원북부산지, 강원중부산지, 강원남부산지), 경상북도(영덕, 울진평지, 포항, 경주, 경북북동산지), 경상남도(양산, 창원, 김해, 밀양), 부산, 울산"
  },
  "202212031600": {
    "제목": "풍랑주의보·한파경보·한파주의보 발표",
    "해당구역": "(1) 풍랑주의보 발표 : 동해중부안쪽먼바다, 동해중부바깥먼바다\r\n(2) 한파경보 발표 : 강원도(철원, 화천, 강원북부산지, 강원중부산지)\r\n(3) 한파주의보 발표 : 경기도(연천, 포천), 강원도(태백, 평창평지, 횡성, 원주, 홍천평지, 춘천, 양구평지, 인제평지, 강원남부산지)",
    "발효시각": "(1) 풍랑주의보 발표 : 2022년 12월 03일 18시 00분\r\n(2) 한파경보 발표 : 2022년 12월 03일 23시 00분\r\n(3) 한파주의보 발표 : 2022년 12월 03일 23시 00분",
    "내용": "(1) 풍랑주의보 발표\r\n  o 해제 예고: 5일 새벽(00시~03시)",
    "특보발효현황내용": 202212032300,
    "예비특보": "o 강풍주의보 : 강원도(태백, 속초평지, 고성평지, 양양평지, 정선평지, 강원북부산지, 강원중부산지, 강원남부산지)\r\no 풍랑주의보 : 동해중부안쪽먼바다, 동해중부바깥먼바다\r\no 한파경보 : 강원도(철원, 화천, 강원북부산지, 강원중부산지)\r\no 한파주의보 : 경기도(연천, 포천), 강원도(태백, 평창평지, 횡성, 원주, 홍천평지, 춘천, 양구평지, 인제평지, 강원남부산지)\r\no 건조주의보 : 강원도(강릉평지, 동해평지, 태백, 삼척평지, 속초평지, 고성평지, 양양평지, 강원북부산지, 강원중부산지, 강원남부산지), 경상북도(영덕, 울진평지, 포항, 경주, 경북북동산지), 경상남도(양산, 창원, 김해, 밀양), 부산, 울산"
  },
  "202212030700": {
    "제목": "강풍주의보 발표",
    "해당구역": "(1) 강풍주의보 발표 : 강원도(속초평지, 고성평지, 양양평지)",
    "발효시각": "(1) 강풍주의보 발표 : 2022년 12월 03일 07시 00분",
    "내용": "(1) 강풍주의보 발표\r\n  o 해제 예고: 4일 새벽(00시~03시)",
    "특보발효현황내용": 202212030700,
    "예비특보": "o 강풍주의보 : 강원도(태백, 속초평지, 고성평지, 양양평지, 정선평지, 강원북부산지, 강원중부산지, 강원남부산지)\r\no 건조주의보 : 강원도(강릉평지, 동해평지, 태백, 삼척평지, 속초평지, 고성평지, 양양평지, 강원북부산지, 강원중부산지, 강원남부산지), 경상북도(영덕, 울진평지, 포항, 경주, 경북북동산지), 경상남도(양산, 창원, 김해, 밀양), 부산, 울산"
  },
  "202212030200": {
    "제목": "강풍주의보 발표",
    "해당구역": "(1) 강풍주의보 발표 : 강원도(태백, 정선평지, 강원북부산지, 강원중부산지, 강원남부산지)",
    "발효시각": "(1) 강풍주의보 발표 : 2022년 12월 03일 04시 00분",
    "내용": "(1) 강풍주의보 발표\r\n  o 해제 예고: 4일 새벽(00시~03시)",
    "특보발효현황내용": 202212030400,
    "예비특보": "o 강풍주의보 : 강원도(태백, 정선평지, 강원북부산지, 강원중부산지, 강원남부산지)\r\no 건조주의보 : 강원도(강릉평지, 동해평지, 태백, 삼척평지, 속초평지, 고성평지, 양양평지, 강원북부산지, 강원중부산지, 강원남부산지), 경상북도(영덕, 울진평지, 포항, 경주, 경북북동산지), 경상남도(양산, 창원, 김해, 밀양), 부산, 울산"
  },
  "202212021600": {
    "제목": "건조주의보 해제",
    "해당구역": "(1) 건조주의보 해제 : 경기도(광명, 과천, 부천, 성남, 안양, 구리, 오산, 군포, 의왕, 하남, 광주), 강원도(정선평지, 철원, 화천, 양구평지), 서울",
    "발효시각": "(1) 건조주의보 해제 : 2022년 12월 02일 19시 00분",
    "내용": "",
    "특보발효현황내용": 202212021900,
    "예비특보": "o 건조주의보 : 강원도(강릉평지, 동해평지, 태백, 삼척평지, 속초평지, 고성평지, 양양평지, 강원북부산지, 강원중부산지, 강원남부산지), 경상북도(영덕, 울진평지, 포항, 경주, 경북북동산지), 경상남도(양산, 창원, 김해, 밀양), 부산, 울산"
  },
  "202212021000": {
    "제목": "풍랑주의보·한파경보·한파주의보 해제",
    "해당구역": "(1) 한파경보 해제 : 강원도(철원, 화천, 강원북부산지, 강원중부산지)\r\n(2) 한파주의보 해제 : 경기도(동두천, 연천, 포천, 가평, 양주, 의정부, 파주, 남양주, 여주, 양평), 강원도(태백, 영월, 평창평지, 정선평지, 횡성, 원주, 홍천평지, 춘천, 양구평지, 인제평지, 강원남부산지), 충청북도(괴산, 충주, 제천, 단양)\r\n(3) 풍랑주의보 해제 : 동해남부북쪽바깥먼바다, 동해중부안쪽먼바다, 동해중부바깥먼바다",
    "발효시각": "(1) 한파경보 해제 : 2022년 12월 02일 10시 00분\r\n(2) 한파주의보 해제 : 2022년 12월 02일 10시 00분\r\n(3) 풍랑주의보 해제 : 2022년 12월 02일 12시 00분",
    "내용": "",
    "특보발효현황내용": 202212021200,
    "예비특보": "o 건조주의보 : 경기도(광명, 과천, 부천, 성남, 안양, 구리, 오산, 군포, 의왕, 하남, 광주), 강원도(강릉평지, 동해평지, 태백, 삼척평지, 속초평지, 고성평지, 양양평지, 정선평지, 철원, 화천, 양구평지, 강원북부산지, 강원중부산지, 강원남부산지), 경상북도(영덕, 울진평지, 포항, 경주, 경북북동산지), 경상남도(양산, 창원, 김해, 밀양), 서울, 부산, 울산"
  },
  "202212020900": {
    "제목": "대설주의보 해제",
    "해당구역": "(1) 대설주의보 해제 : 제주도(제주도산지)",
    "발효시각": "(1) 대설주의보 해제 : 2022년 12월 02일 09시 00분",
    "내용": "",
    "특보발효현황내용": 202212020900,
    "예비특보": "o 풍랑주의보 : 동해남부북쪽바깥먼바다, 동해중부안쪽먼바다, 동해중부바깥먼바다\r\no 한파경보 : 강원도(철원, 화천, 강원북부산지, 강원중부산지)\r\no 한파주의보 : 경기도(동두천, 연천, 포천, 가평, 양주, 의정부, 파주, 남양주, 여주, 양평), 강원도(태백, 영월, 평창평지, 정선평지, 횡성, 원주, 홍천평지, 춘천, 양구평지, 인제평지, 강원남부산지), 충청북도(괴산, 충주, 제천, 단양)\r\no 건조주의보 : 경기도(광명, 과천, 부천, 성남, 안양, 구리, 오산, 군포, 의왕, 하남, 광주), 강원도(강릉평지, 동해평지, 태백, 삼척평지, 속초평지, 고성평지, 양양평지, 정선평지, 철원, 화천, 양구평지, 강원북부산지, 강원중부산지, 강원남부산지), 경상북도(영덕, 울진평지, 포항, 경주, 경북북동산지), 경상남도(양산, 창원, 김해, 밀양), 서울, 부산, 울산"
  },
  "202212020650": {
    "제목": "대설주의보 발표",
    "해당구역": "(1) 대설주의보 발표 : 제주도(제주도산지)",
    "발효시각": "(1) 대설주의보 발표 : 2022년 12월 02일 06시 50분",
    "내용": "",
    "특보발효현황내용": 202212020650,
    "예비특보": "o 풍랑주의보 : 동해남부북쪽바깥먼바다, 동해중부안쪽먼바다, 동해중부바깥먼바다\r\no 대설주의보 : 제주도(제주도산지)\r\no 한파경보 : 강원도(철원, 화천, 강원북부산지, 강원중부산지)\r\no 한파주의보 : 경기도(동두천, 연천, 포천, 가평, 양주, 의정부, 파주, 남양주, 여주, 양평), 강원도(태백, 영월, 평창평지, 정선평지, 횡성, 원주, 홍천평지, 춘천, 양구평지, 인제평지, 강원남부산지), 충청북도(괴산, 충주, 제천, 단양)\r\no 건조주의보 : 경기도(광명, 과천, 부천, 성남, 안양, 구리, 오산, 군포, 의왕, 하남, 광주), 강원도(강릉평지, 동해평지, 태백, 삼척평지, 속초평지, 고성평지, 양양평지, 정선평지, 철원, 화천, 양구평지, 강원북부산지, 강원중부산지, 강원남부산지), 경상북도(영덕, 울진평지, 포항, 경주, 경북북동산지), 경상남도(양산, 창원, 김해, 밀양), 서울, 부산, 울산"
  },
  "202212011700": {
    "제목": "강풍주의보·풍랑주의보 해제",
    "해당구역": "(1) 강풍주의보 해제 : 울릉도.독도\r\n(2) 풍랑주의보 해제 : 동해남부북쪽안쪽먼바다",
    "발효시각": "(1) 강풍주의보 해제 : 2022년 12월 01일 19시 00분\r\n(2) 풍랑주의보 해제 : 2022년 12월 01일 19시 00분",
    "내용": "",
    "특보발효현황내용": 202212011900,
    "예비특보": "o 풍랑주의보 : 동해남부북쪽바깥먼바다, 동해중부안쪽먼바다, 동해중부바깥먼바다\r\no 한파경보 : 강원도(철원, 화천, 강원북부산지, 강원중부산지)\r\no 한파주의보 : 경기도(동두천, 연천, 포천, 가평, 양주, 의정부, 파주, 남양주, 여주, 양평), 강원도(태백, 영월, 평창평지, 정선평지, 횡성, 원주, 홍천평지, 춘천, 양구평지, 인제평지, 강원남부산지), 충청북도(괴산, 충주, 제천, 단양)\r\no 건조주의보 : 경기도(광명, 과천, 부천, 성남, 안양, 구리, 오산, 군포, 의왕, 하남, 광주), 강원도(강릉평지, 동해평지, 태백, 삼척평지, 속초평지, 고성평지, 양양평지, 정선평지, 철원, 화천, 양구평지, 강원북부산지, 강원중부산지, 강원남부산지), 경상북도(영덕, 울진평지, 포항, 경주, 경북북동산지), 경상남도(양산, 창원, 김해, 밀양), 서울, 부산, 울산"
  },
  "202212011600": {
    "제목": "대설주의보 해제",
    "해당구역": "(1) 대설주의보 해제 : 서해5도",
    "발효시각": "(1) 대설주의보 해제 : 2022년 12월 01일 16시 00분",
    "내용": "",
    "특보발효현황내용": 202212011600,
    "예비특보": "o 강풍주의보 : 울릉도.독도\r\no 풍랑주의보 : 동해남부북쪽안쪽먼바다, 동해남부북쪽바깥먼바다, 동해중부안쪽먼바다, 동해중부바깥먼바다\r\no 한파경보 : 강원도(철원, 화천, 강원북부산지, 강원중부산지)\r\no 한파주의보 : 경기도(동두천, 연천, 포천, 가평, 양주, 의정부, 파주, 남양주, 여주, 양평), 강원도(태백, 영월, 평창평지, 정선평지, 횡성, 원주, 홍천평지, 춘천, 양구평지, 인제평지, 강원남부산지), 충청북도(괴산, 충주, 제천, 단양)\r\no 건조주의보 : 경기도(광명, 과천, 부천, 성남, 안양, 구리, 오산, 군포, 의왕, 하남, 광주), 강원도(강릉평지, 동해평지, 태백, 삼척평지, 속초평지, 고성평지, 양양평지, 정선평지, 철원, 화천, 양구평지, 강원북부산지, 강원중부산지, 강원남부산지), 경상북도(영덕, 울진평지, 포항, 경주, 경북북동산지), 경상남도(양산, 창원, 김해, 밀양), 서울, 부산, 울산"
  },
  "202212011010": {
    "제목": "풍랑주의보 해제·건조주의보 발표",
    "해당구역": "(1) 건조주의보 발표 : 강원도(정선평지, 철원, 화천, 양구평지), 경상남도(양산), 부산\r\n(2) 풍랑주의보 해제 : 제주도남쪽바깥먼바다\r\n(3) 풍랑주의보 해제 : 동해남부남쪽안쪽먼바다, 동해남부남쪽바깥먼바다, 남해동부바깥먼바다",
    "발효시각": "(1) 건조주의보 발표 : 2022년 12월 01일 10시 10분\r\n(2) 풍랑주의보 해제 : 2022년 12월 01일 12시 00분\r\n(3) 풍랑주의보 해제 : 2022년 12월 01일 13시 00분",
    "내용": "",
    "특보발효현황내용": 202212011300,
    "예비특보": "o 강풍주의보 : 울릉도.독도\r\no 풍랑주의보 : 동해남부북쪽안쪽먼바다, 동해남부북쪽바깥먼바다, 동해중부안쪽먼바다, 동해중부바깥먼바다\r\no 대설주의보 : 서해5도\r\no 한파경보 : 강원도(철원, 화천, 강원북부산지, 강원중부산지)\r\no 한파주의보 : 경기도(동두천, 연천, 포천, 가평, 양주, 의정부, 파주, 남양주, 여주, 양평), 강원도(태백, 영월, 평창평지, 정선평지, 횡성, 원주, 홍천평지, 춘천, 양구평지, 인제평지, 강원남부산지), 충청북도(괴산, 충주, 제천, 단양)\r\no 건조주의보 : 경기도(광명, 과천, 부천, 성남, 안양, 구리, 오산, 군포, 의왕, 하남, 광주), 강원도(강릉평지, 동해평지, 태백, 삼척평지, 속초평지, 고성평지, 양양평지, 정선평지, 철원, 화천, 양구평지, 강원북부산지, 강원중부산지, 강원남부산지), 경상북도(영덕, 울진평지, 포항, 경주, 경북북동산지), 경상남도(양산, 창원, 김해, 밀양), 서울, 부산, 울산"
  },
  "202212011000": {
    "제목": "한파경보 해제·한파주의보 변경·한파주의보 해제",
    "해당구역": "(1) 한파경보 해제 : 경기도(광명, 과천, 부천, 김포, 고양, 수원, 성남, 안양, 구리, 군포, 의왕, 하남, 용인, 이천, 안성, 광주), 경상북도(영주, 봉화평지, 경북북동산지), 서울, 인천(강화)\r\n(2) 한파주의보 해제 : 경기도(안산, 시흥, 오산, 평택, 화성), 강원도(강릉평지, 동해평지, 삼척평지, 속초평지, 고성평지, 양양평지), 충청남도, 충청북도(청주, 보은, 옥천, 영동, 진천, 음성, 증평), 전라남도(흑산도.홍도, 거문도.초도 제외), 전라북도, 경상북도(영주, 봉화평지, 경북북동산지 제외), 경상남도, 제주도(제주도산지), 인천(강화군 제외), 대전, 광주, 대구, 부산, 울산, 세종\r\n(3) 한파주의보 변경 : 경기도(동두천, 연천, 포천, 가평, 양주, 의정부, 파주, 남양주, 여주, 양평), 강원도(태백, 영월, 평창평지, 정선평지, 횡성, 원주, 홍천평지, 춘천, 양구평지, 인제평지, 강원남부산지)",
    "발효시각": "(1) 한파경보 해제 : 2022년 12월 01일 10시 00분\r\n(2) 한파주의보 해제 : 2022년 12월 01일 10시 00분\r\n(3) 한파주의보 변경 : 2022년 12월 01일 10시 00분",
    "내용": "",
    "특보발효현황내용": 202212011000,
    "예비특보": "o 강풍주의보 : 울릉도.독도\r\no 풍랑주의보 : 동해남부남쪽안쪽먼바다, 동해남부남쪽바깥먼바다, 동해남부북쪽안쪽먼바다, 동해남부북쪽바깥먼바다, 동해중부안쪽먼바다, 동해중부바깥먼바다, 남해동부바깥먼바다, 제주도남쪽바깥먼바다\r\no 대설주의보 : 서해5도\r\no 한파경보 : 강원도(철원, 화천, 강원북부산지, 강원중부산지)\r\no 한파주의보 : 경기도(동두천, 연천, 포천, 가평, 양주, 의정부, 파주, 남양주, 여주, 양평), 강원도(태백, 영월, 평창평지, 정선평지, 횡성, 원주, 홍천평지, 춘천, 양구평지, 인제평지, 강원남부산지), 충청북도(괴산, 충주, 제천, 단양)\r\no 건조주의보 : 경기도(광명, 과천, 부천, 성남, 안양, 구리, 오산, 군포, 의왕, 하남, 광주), 강원도(강릉평지, 동해평지, 태백, 삼척평지, 속초평지, 고성평지, 양양평지, 강원북부산지, 강원중부산지, 강원남부산지), 경상북도(영덕, 울진평지, 포항, 경주, 경북북동산지), 경상남도(창원, 김해, 밀양), 서울, 울산"
  },
  "202212010920": {
    "제목": "대설주의보 발표",
    "해당구역": "(1) 대설주의보 발표 : 서해5도",
    "발효시각": "(1) 대설주의보 발표 : 2022년 12월 01일 09시 20분",
    "내용": "",
    "특보발효현황내용": 202212010920,
    "예비특보": "o 강풍주의보 : 울릉도.독도\r\no 풍랑주의보 : 동해남부남쪽안쪽먼바다, 동해남부남쪽바깥먼바다, 동해남부북쪽안쪽먼바다, 동해남부북쪽바깥먼바다, 동해중부안쪽먼바다, 동해중부바깥먼바다, 남해동부바깥먼바다, 제주도남쪽바깥먼바다\r\no 대설주의보 : 서해5도\r\no 한파경보 : 경기도(안산, 시흥, 오산, 평택, 화성 제외), 강원도(태백, 영월, 평창평지, 정선평지, 횡성, 원주, 철원, 화천, 홍천평지, 춘천, 양구평지, 인제평지, 강원북부산지, 강원중부산지, 강원남부산지), 경상북도(영주, 봉화평지, 경북북동산지), 서울, 인천(강화)\r\no 한파주의보 : 경기도(안산, 시흥, 오산, 평택, 화성), 강원도(강릉평지, 동해평지, 삼척평지, 속초평지, 고성평지, 양양평지), 충청남도, 충청북도, 전라남도(흑산도.홍도, 거문도.초도 제외), 전라북도, 경상북도(영주, 봉화평지, 경북북동산지 제외), 경상남도, 제주도(제주도산지), 인천(강화군 제외), 대전, 광주, 대구, 부산, 울산, 세종\r\no 건조주의보 : 경기도(광명, 과천, 부천, 성남, 안양, 구리, 오산, 군포, 의왕, 하남, 광주), 강원도(강릉평지, 동해평지, 태백, 삼척평지, 속초평지, 고성평지, 양양평지, 강원북부산지, 강원중부산지, 강원남부산지), 경상북도(영덕, 울진평지, 포항, 경주, 경북북동산지), 경상남도(창원, 김해, 밀양), 서울, 울산"
  },
  "202212010600": {
    "제목": "풍랑주의보 해제",
    "해당구역": "(1) 풍랑주의보 해제 : 서해남부남쪽안쪽먼바다, 서해남부남쪽바깥먼바다, 제주도남동쪽안쪽먼바다, 제주도남서쪽안쪽먼바다",
    "발효시각": "(1) 풍랑주의보 해제 : 2022년 12월 01일 09시 00분",
    "내용": "",
    "특보발효현황내용": 202212010900,
    "예비특보": "o 강풍주의보 : 울릉도.독도\r\no 풍랑주의보 : 동해남부남쪽안쪽먼바다, 동해남부남쪽바깥먼바다, 동해남부북쪽안쪽먼바다, 동해남부북쪽바깥먼바다, 동해중부안쪽먼바다, 동해중부바깥먼바다, 남해동부바깥먼바다, 제주도남쪽바깥먼바다\r\no 한파경보 : 경기도(안산, 시흥, 오산, 평택, 화성 제외), 강원도(태백, 영월, 평창평지, 정선평지, 횡성, 원주, 철원, 화천, 홍천평지, 춘천, 양구평지, 인제평지, 강원북부산지, 강원중부산지, 강원남부산지), 경상북도(영주, 봉화평지, 경북북동산지), 서울, 인천(강화)\r\no 한파주의보 : 경기도(안산, 시흥, 오산, 평택, 화성), 강원도(강릉평지, 동해평지, 삼척평지, 속초평지, 고성평지, 양양평지), 충청남도, 충청북도, 전라남도(흑산도.홍도, 거문도.초도 제외), 전라북도, 경상북도(영주, 봉화평지, 경북북동산지 제외), 경상남도, 제주도(제주도산지), 인천(강화군 제외), 대전, 광주, 대구, 부산, 울산, 세종\r\no 건조주의보 : 경기도(광명, 과천, 부천, 성남, 안양, 구리, 오산, 군포, 의왕, 하남, 광주), 강원도(강릉평지, 동해평지, 태백, 삼척평지, 속초평지, 고성평지, 양양평지, 강원북부산지, 강원중부산지, 강원남부산지), 경상북도(영덕, 울진평지, 포항, 경주, 경북북동산지), 경상남도(창원, 김해, 밀양), 서울, 울산"
  },
  "202212010400": {
    "제목": "강풍주의보·풍랑주의보 해제",
    "해당구역": "(1) 강풍주의보 해제 : 전라남도(흑산도.홍도)\r\n(2) 풍랑주의보 해제 : 서해남부북쪽안쪽먼바다, 서해남부북쪽바깥먼바다, 남해서부서쪽먼바다, 제주도앞바다",
    "발효시각": "(1) 강풍주의보 해제 : 2022년 12월 01일 06시 00분\r\n(2) 풍랑주의보 해제 : 2022년 12월 01일 06시 00분",
    "내용": "",
    "특보발효현황내용": 202212010600,
    "예비특보": "o 강풍주의보 : 울릉도.독도\r\no 풍랑주의보 : 동해남부남쪽안쪽먼바다, 동해남부남쪽바깥먼바다, 동해남부북쪽안쪽먼바다, 동해남부북쪽바깥먼바다, 동해중부안쪽먼바다, 동해중부바깥먼바다, 서해남부남쪽안쪽먼바다, 서해남부남쪽바깥먼바다, 남해동부바깥먼바다, 제주도남쪽바깥먼바다, 제주도남동쪽안쪽먼바다, 제주도남서쪽안쪽먼바다\r\no 한파경보 : 경기도(안산, 시흥, 오산, 평택, 화성 제외), 강원도(태백, 영월, 평창평지, 정선평지, 횡성, 원주, 철원, 화천, 홍천평지, 춘천, 양구평지, 인제평지, 강원북부산지, 강원중부산지, 강원남부산지), 경상북도(영주, 봉화평지, 경북북동산지), 서울, 인천(강화)\r\no 한파주의보 : 경기도(안산, 시흥, 오산, 평택, 화성), 강원도(강릉평지, 동해평지, 삼척평지, 속초평지, 고성평지, 양양평지), 충청남도, 충청북도, 전라남도(흑산도.홍도, 거문도.초도 제외), 전라북도, 경상북도(영주, 봉화평지, 경북북동산지 제외), 경상남도, 제주도(제주도산지), 인천(강화군 제외), 대전, 광주, 대구, 부산, 울산, 세종\r\no 건조주의보 : 경기도(광명, 과천, 부천, 성남, 안양, 구리, 오산, 군포, 의왕, 하남, 광주), 강원도(강릉평지, 동해평지, 태백, 삼척평지, 속초평지, 고성평지, 양양평지, 강원북부산지, 강원중부산지, 강원남부산지), 경상북도(영덕, 울진평지, 포항, 경주, 경북북동산지), 경상남도(창원, 김해, 밀양), 서울, 울산"
  }
}